{"image_url": "https://s3-media1.fl.yelpcdn.com/bphoto/7JHZmlxdQ1vgkgqYwnkEiw/o.jpg", "term": "attractions", "is_closed": false, "categories": [{"alias": "hotels", "title": "Hotels"}], "review_count": 36, "is_claimed": true, "phone": "+14087828311", "name": "Residence Inn San Jose South/Morgan Hill", "photos": ["https://s3-media3.fl.yelpcdn.com/bphoto/7JHZmlxdQ1vgkgqYwnkEiw/o.jpg", "https://s3-media3.fl.yelpcdn.com/bphoto/uPVy3IOGulW9PkRQBihWzg/o.jpg", "https://s3-media1.fl.yelpcdn.com/bphoto/zGLznzss61g-Ykv9nn2rOQ/o.jpg"], "rating": 3.0, "location": {"city": "Morgan Hill", "address2": "", "address1": "18620 Madrone Pkwy", "address3": "", "state": "CA", "zip_code": "95037", "country": "US"}, "price": "$$", "hours": [{"is_open_now": true, "open": [{"is_overnight": false, "end": "0000", "start": "0000", "day": 0}, {"is_overnight": false, "end": "0000", "start": "0000", "day": 1}, {"is_overnight": false, "end": "0000", "start": "0000", "day": 2}, {"is_overnight": false, "end": "0000", "start": "0000", "day": 3}, {"is_overnight": false, "end": "0000", "start": "0000", "day": 4}, {"is_overnight": false, "end": "0000", "start": "0000", "day": 5}, {"is_overnight": false, "end": "0000", "start": "0000", "day": 6}], "hours_type": "REGULAR"}], "id": "residence-inn-san-jose-south-morgan-hill-morgan-hill", "coordinates": {"latitude": 37.15326, "longitude": -121.65535}, "url": "https://www.yelp.com/biz/residence-inn-san-jose-south-morgan-hill-morgan-hill?adjust_creative=92p07_JjKyriZTQxAXRiKQ&utm_campaign=yelp_api_v3&utm_medium=api_v3_business_lookup&utm_source=92p07_JjKyriZTQxAXRiKQ"}