{"phone": "+12069380975", "is_claimed": false, "name": "Seacrest Park", "review_count": 11, "location": {"address1": "1660 Harbor Ave. SW", "address3": "", "zip_code": "98126", "state": "WA", "address2": "", "city": "Seattle", "country": "US"}, "categories": [{"title": "Parks", "alias": "parks"}], "url": "https://www.yelp.com/biz/seacrest-park-seattle?adjust_creative=92p07_JjKyriZTQxAXRiKQ&utm_campaign=yelp_api_v3&utm_medium=api_v3_business_lookup&utm_source=92p07_JjKyriZTQxAXRiKQ", "term": "attractions", "rating": 5.0, "id": "seacrest-park-seattle", "image_url": "https://s3-media4.fl.yelpcdn.com/bphoto/kGQ_I7M1sC54UW3U69vFLQ/o.jpg", "photos": ["https://s3-media3.fl.yelpcdn.com/bphoto/kGQ_I7M1sC54UW3U69vFLQ/o.jpg", "https://s3-media3.fl.yelpcdn.com/bphoto/Ou0Z1lXMPQQr78as39JB4g/o.jpg", "https://s3-media4.fl.yelpcdn.com/bphoto/WaVedQKDysPCgcAP2Q0mAQ/o.jpg"], "hours": [{"hours_type": "REGULAR", "is_open_now": false, "open": [{"day": 0, "end": "2330", "is_overnight": false, "start": "0400"}, {"day": 1, "end": "2330", "is_overnight": false, "start": "0400"}, {"day": 2, "end": "2330", "is_overnight": false, "start": "0400"}, {"day": 3, "end": "2330", "is_overnight": false, "start": "0400"}, {"day": 4, "end": "2330", "is_overnight": false, "start": "0400"}, {"day": 5, "end": "2330", "is_overnight": false, "start": "0400"}, {"day": 6, "end": "2330", "is_overnight": false, "start": "0400"}]}], "is_closed": false, "coordinates": {"longitude": -122.3806746, "latitude": 47.589018}}