{"abstract": null, "web_url": "http://www.nytimes.com/aponline/2016/01/09/sports/ncaabasketball/ap-bkc-t25-arizona-usc.html", "byline": {"original": "By THE ASSOCIATED PRESS", "person": [], "organization": "THE ASSOCIATED PRESS"}, "subsection_name": "College Basketball", "type_of_material": "News", "lead_paragraph": "In spurts, Elijah Stewart felt bone-tired. His voice was nearly gone, too. His mind wandered to last season's triple-overtime loss to Colorado, too.", "_id": "5691cc3438f0d86c10aeeb06", "word_count": "813", "news_desk": "None", "print_page": null, "keywords": [], "multimedia": [], "headline": {"print_headline": "Southern California Edges No. 7 Arizona 103-101 in 4 OTs", "main": "Southern California Edges No. 7 Arizona 103-101 in 4 OTs"}, "pub_date": "2016-01-09T22:11:00Z", "slideshow_credits": null, "document_type": "article", "source": "AP", "snippet": "In spurts, Elijah Stewart felt bone-tired. His voice was nearly gone, too. His mind wandered to last season's triple-overtime loss to Colorado, too....", "blog": [], "section_name": "Sports"}