{"abstract": null, "web_url": "http://www.nytimes.com/aponline/2016/01/31/sports/ncaabasketball/ap-bkw-t25-missouri-mississippi.html", "byline": {"original": "By THE ASSOCIATED PRESS", "person": [], "organization": "THE ASSOCIATED PRESS"}, "subsection_name": "College Basketball", "type_of_material": "News", "lead_paragraph": "Sierra Michaelis scored 20 points with eight rebounds and five assists and No. 22 Missouri handled Mississippi 60-46 on Sunday.", "_id": "56aea51838f0d82f06c0cc8a", "word_count": "162", "news_desk": "None", "print_page": null, "keywords": [], "multimedia": [], "headline": {"print_headline": "Michaelis Scores 20, No. 22 Missouri Handles Ole Miss 60-46", "main": "Michaelis Scores 20, No. 22 Missouri Handles Ole Miss 60-46"}, "pub_date": "2016-01-31T19:20:19Z", "slideshow_credits": null, "document_type": "article", "source": "AP", "snippet": "Sierra Michaelis scored 20 points with eight rebounds and five assists and No. 22 Missouri handled Mississippi 60-46 on Sunday....", "blog": [], "section_name": "Sports"}