{"abstract": null, "web_url": "http://www.nytimes.com/aponline/2016/01/31/sports/ncaabasketball/ap-bkw-t25-south-carolina-texas-am.html", "byline": {"original": "By THE ASSOCIATED PRESS", "person": [], "organization": "THE ASSOCIATED PRESS"}, "subsection_name": "College Basketball", "type_of_material": "News", "lead_paragraph": "A'ja Wilson scored 27 points and Tiffany Mitchell added 20 as No. 2 South Carolina stayed unbeaten by holding on for a 70-63 victory over No. 10 Texas A&amp;M on Sunday night.", "_id": "56aeb27938f0d82f06c0cc9c", "word_count": "378", "news_desk": "None", "print_page": null, "keywords": [], "multimedia": [], "headline": {"print_headline": "Wilson's 27 Points Lifts No. 2 South Carolina Over Texas A&M", "main": "Wilson's 27 Points Lifts No. 2 South Carolina Over Texas A&M"}, "pub_date": "2016-01-31T20:16:35Z", "slideshow_credits": null, "document_type": "article", "source": "AP", "snippet": "A'ja Wilson scored 27 points and Tiffany Mitchell added 20 as No. 2 South Carolina stayed unbeaten by holding on for a 70-63 victory over No. 10 Texas A&amp;M on Sunday night....", "blog": [], "section_name": "Sports"}