{"document_type": "article", "byline": [], "news_desk": "Society", "slideshow_credits": null, "abstract": null, "multimedia": [{"type": "image", "url": "images/2016/08/07/fashion/weddings/07WANG/07WANG-thumbWide-v2.jpg", "legacy": {"wide": "images/2016/08/07/fashion/weddings/07WANG/07WANG-thumbWide-v2.jpg", "wideheight": "126", "widewidth": "190"}, "width": 190, "subtype": "wide", "height": 126}, {"type": "image", "url": "images/2016/08/07/fashion/weddings/07WANG/07WANG-articleLarge-v2.jpg", "legacy": {"xlarge": "images/2016/08/07/fashion/weddings/07WANG/07WANG-articleLarge-v2.jpg", "xlargewidth": "600", "xlargeheight": "354"}, "width": 600, "subtype": "xlarge", "height": 354}, {"type": "image", "url": "images/2016/08/07/fashion/weddings/07WANG/07WANG-thumbStandard.jpg", "legacy": {"thumbnail": "images/2016/08/07/fashion/weddings/07WANG/07WANG-thumbStandard.jpg", "thumbnailwidth": "75", "thumbnailheight": "75"}, "width": 75, "subtype": "thumbnail", "height": 75}], "headline": {"print_headline": "Rachel Wang,  Mark Levey", "main": "Rachel Wang, Mark Levey"}, "print_page": "13", "keywords": [{"value": "Weddings and Engagements", "is_major": "N", "rank": "1", "name": "subject"}, {"value": "Pearl River (NY)", "is_major": "N", "rank": "2", "name": "glocations"}, {"value": "Rutgers, The State University of New Jersey", "is_major": "N", "rank": "3", "name": "organizations"}, {"value": "Brooklyn (NYC)", "is_major": "N", "rank": "4", "name": "glocations"}], "snippet": "The couple, who met at a concert in Brooklyn in 2012, were married in Pearl River, N.Y....", "source": "The New York Times", "lead_paragraph": "The couple, who met at a concert in Brooklyn in 2012, were married in Pearl River, N.Y.", "word_count": "232", "pub_date": "2016-08-07T04:00:00+0000", "subsection_name": "Weddings", "blog": [], "type_of_material": "News", "section_name": "Fashion & Style", "web_url": "http://www.nytimes.com/2016/08/07/fashion/weddings/rachel-wang-mark-levey.html", "_id": "57aa292995d0e021d797f1d5"}