{"abstract": "NBA Roundup; Cleveland Cavaliers defeat Brooklyn Nets, 107-87; other basketball scores noted.", "web_url": "http://www.nytimes.com/2016/04/01/sports/basketball/lebron-james-moves-up-scoring-list-as-cavs-beat-nets.html", "byline": {"person": [], "original": "By THE ASSOCIATED PRESS", "contributor": "", "organization": "THE ASSOCIATED PRESS"}, "subsection_name": "Pro Basketball", "type_of_material": "News", "lead_paragraph": "LeBron James scored 24 points to pass Dominique Wilkins, and the Cleveland Cavaliers beat the Nets, 107-87.", "_id": "56fdf8a538f0d85faa67c5ad", "word_count": "416", "news_desk": "Sports", "print_page": "12", "keywords": [{"value": "Basketball", "is_major": "Y", "rank": "1", "name": "subject"}, {"value": "James, LeBron", "is_major": "N", "rank": "2", "name": "persons"}, {"value": "Brooklyn Nets", "is_major": "Y", "rank": "3", "name": "organizations"}, {"value": "Cleveland Cavaliers", "is_major": "Y", "rank": "4", "name": "organizations"}], "multimedia": [], "headline": {"content_kicker": "N.B.A. Roundup", "print_headline": "LeBron James Moves Up Scoring List as Cavs Beat Nets", "main": "LeBron James Moves Up Scoring List as Cavs Beat Nets"}, "pub_date": "2016-04-01T00:00:00Z", "slideshow_credits": null, "document_type": "article", "source": "The New York Times", "snippet": "LeBron James scored 24 points to pass Dominique Wilkins, and the Cleveland Cavaliers beat the Nets, 107-87....", "blog": [], "section_name": "Sports"}