{"document_type": "article", "byline": {"person": [], "organization": "THE ASSOCIATED PRESS", "original": "By THE ASSOCIATED PRESS"}, "news_desk": "Sports", "slideshow_credits": null, "abstract": null, "multimedia": [{"type": "image", "url": "images/2016/10/16/sports/16playerdies-web2/16playerdies-web2-thumbWide.jpg", "legacy": {"wide": "images/2016/10/16/sports/16playerdies-web2/16playerdies-web2-thumbWide.jpg", "wideheight": "126", "widewidth": "190"}, "width": 190, "subtype": "wide", "height": 126}, {"type": "image", "url": "images/2016/10/16/sports/16playerdies-web2/16playerdies-web2-articleLarge.jpg", "legacy": {"xlarge": "images/2016/10/16/sports/16playerdies-web2/16playerdies-web2-articleLarge.jpg", "xlargewidth": "600", "xlargeheight": "400"}, "width": 600, "subtype": "xlarge", "height": 400}, {"type": "image", "url": "images/2016/10/16/sports/16playerdies-web2/16playerdies-web2-thumbStandard.jpg", "legacy": {"thumbnail": "images/2016/10/16/sports/16playerdies-web2/16playerdies-web2-thumbStandard.jpg", "thumbnailwidth": "75", "thumbnailheight": "75"}, "width": 75, "subtype": "thumbnail", "height": 75}], "headline": {"print_headline": "A Former Star at Auburn Dies in His Sleep at Age 32", "main": "Quentin Groves, Former Auburn Star, Dies in His Sleep at 32"}, "print_page": "4", "keywords": [{"value": "Football (College)", "is_major": "N", "rank": "1", "name": "subject"}, {"value": "Groves, Quentin (1984-2016)", "is_major": "N", "rank": "2", "name": "persons"}, {"value": "Deaths (Obituaries)", "is_major": "N", "rank": "3", "name": "subject"}, {"value": "Auburn University", "is_major": "N", "rank": "4", "name": "organizations"}], "snippet": "Groves, a defensive end, was visiting Trinidad, his wife\u2019s native country....", "source": "The New York Times", "lead_paragraph": "Groves, a defensive end, was visiting Trinidad, his wife\u2019s native country.", "word_count": "190", "pub_date": "2016-10-16T04:00:00+0000", "subsection_name": "College Football", "blog": [], "type_of_material": "Obituary (Obit)", "section_name": "Sports", "web_url": "http://www.nytimes.com/2016/10/16/sports/ncaafootball/quentin-groves-former-auburn-star-dies-in-his-sleep-at-32.html", "_id": "5802839895d0e022439c3649"}