{"document_type": "article", "byline": null, "news_desk": "Weekend", "slideshow_credits": null, "abstract": null, "multimedia": [{"type": "image", "url": "images/2016/10/21/arts/21LISTINGSPOP/21LISTINGSPOP-thumbWide.jpg", "legacy": {"wide": "images/2016/10/21/arts/21LISTINGSPOP/21LISTINGSPOP-thumbWide.jpg", "wideheight": "126", "widewidth": "190"}, "width": 190, "subtype": "wide", "height": 126}, {"type": "image", "url": "images/2016/10/21/arts/21LISTINGSPOP/21LISTINGSPOP-articleLarge.jpg", "legacy": {"xlarge": "images/2016/10/21/arts/21LISTINGSPOP/21LISTINGSPOP-articleLarge.jpg", "xlargewidth": "600", "xlargeheight": "400"}, "width": 600, "subtype": "xlarge", "height": 400}, {"type": "image", "url": "images/2016/10/21/arts/21LISTINGSPOP/21LISTINGSPOP-thumbStandard.jpg", "legacy": {"thumbnail": "images/2016/10/21/arts/21LISTINGSPOP/21LISTINGSPOP-thumbStandard.jpg", "thumbnailwidth": "75", "thumbnailheight": "75"}, "width": 75, "subtype": "thumbnail", "height": 75}], "headline": {"print_headline": "The Listings: Pop", "main": "Pop &amp; Rock Listings for Oct. 21-27"}, "print_page": "14", "keywords": [{"value": "Pop and Rock Music", "is_major": "N", "rank": "1", "name": "subject"}], "snippet": "A selected guide to concerts in the New York City area....", "source": "The New York Times", "lead_paragraph": "A selected guide to concerts in the New York City area.", "word_count": "996", "pub_date": "2016-10-21T01:20:31+0000", "subsection_name": "Music", "blog": [], "type_of_material": "Schedule", "section_name": "Arts", "web_url": "http://www.nytimes.com/2016/10/21/arts/music/pop-amp-rock-listings-for-oct-21-27.html", "_id": "58096d6495d0e022439c462d"}