{"abstract": null, "web_url": "http://www.nytimes.com/reuters/2016/03/02/sports/cycling/02reuters-cycling-worlds.html", "byline": {"original": "By REUTERS", "person": [], "organization": "REUTERS"}, "subsection_name": "Cycling", "type_of_material": "News", "lead_paragraph": "Australia's Rebecca Wiasak overwhelmed Poland's Malgorzata Wojtyra to retain her individual pursuit title as the world track championships began at London's velodrome on Wednesday.", "_id": "56d74e2238f0d8655e09bada", "word_count": "355", "news_desk": "None", "print_page": null, "keywords": [], "multimedia": [], "headline": {"print_headline": "Australian Wiasak Retains World Pursuit Title", "main": "Australian Wiasak Retains World Pursuit Title"}, "pub_date": "2016-03-02T15:31:45Z", "slideshow_credits": null, "document_type": "article", "source": "Reuters", "snippet": "Australia's Rebecca Wiasak overwhelmed Poland's Malgorzata Wojtyra to retain her individual pursuit title as the world track championships began at London's velodrome on Wednesday....", "blog": [], "section_name": "Sports"}