{"image_url": "https://s3-media3.fl.yelpcdn.com/bphoto/yHFvDGKFjU6YHucRWZTU0w/o.jpg", "term": "restaurants", "is_closed": false, "categories": [{"alias": "indpak", "title": "Indian"}], "review_count": 53, "is_claimed": true, "phone": "+442074070333", "name": "Mango Indian", "photos": ["https://s3-media2.fl.yelpcdn.com/bphoto/yHFvDGKFjU6YHucRWZTU0w/o.jpg", "https://s3-media3.fl.yelpcdn.com/bphoto/wNc_hL0pgHZT12tAp7v48Q/o.jpg", "https://s3-media2.fl.yelpcdn.com/bphoto/Ozpnt20KI5QT-e1zWI6F7g/o.jpg"], "rating": 4.5, "location": {"city": "London", "address2": "Redcross Way", "address1": "5-6 Cromwell Building", "address3": "", "state": "XGL", "zip_code": "SE1 9HR", "country": "GB"}, "price": "\u00a3\u00a3", "hours": [{"is_open_now": false, "open": [{"is_overnight": false, "end": "1430", "start": "1200", "day": 0}, {"is_overnight": false, "end": "2300", "start": "1730", "day": 0}, {"is_overnight": false, "end": "1430", "start": "1200", "day": 1}, {"is_overnight": false, "end": "2300", "start": "1730", "day": 1}, {"is_overnight": false, "end": "1430", "start": "1200", "day": 2}, {"is_overnight": false, "end": "2300", "start": "1730", "day": 2}, {"is_overnight": false, "end": "1430", "start": "1200", "day": 3}, {"is_overnight": false, "end": "2300", "start": "1730", "day": 3}, {"is_overnight": false, "end": "1430", "start": "1200", "day": 4}, {"is_overnight": false, "end": "2300", "start": "1730", "day": 4}, {"is_overnight": false, "end": "1430", "start": "1200", "day": 5}, {"is_overnight": false, "end": "2300", "start": "1730", "day": 5}, {"is_overnight": false, "end": "1430", "start": "1200", "day": 6}, {"is_overnight": false, "end": "2230", "start": "1730", "day": 6}], "hours_type": "REGULAR"}], "id": "mango-indian-london", "coordinates": {"latitude": 51.5050367, "longitude": -0.0927657}, "url": "https://www.yelp.com/biz/mango-indian-london?adjust_creative=92p07_JjKyriZTQxAXRiKQ&utm_campaign=yelp_api_v3&utm_medium=api_v3_business_lookup&utm_source=92p07_JjKyriZTQxAXRiKQ"}