{"document_type": "article", "byline": {"person": [], "organization": "THE ASSOCIATED PRESS", "original": "By THE ASSOCIATED PRESS"}, "news_desk": "Foreign", "slideshow_credits": null, "abstract": null, "multimedia": [], "headline": {"content_kicker": "World Briefing", "print_headline": "Angola: Members of Book Club Are Convicted of Plotting a Coup", "main": "Angola: Members of Book Club Are Convicted of Plotting a Coup"}, "print_page": "", "keywords": [{"value": "Coups D'Etat and Attempted Coups D'Etat", "is_major": "N", "rank": "1", "name": "subject"}, {"value": "Angola", "is_major": "N", "rank": "2", "name": "glocations"}, {"value": "Luanda Book Club", "is_major": "N", "rank": "3", "name": "organizations"}], "snippet": "A group of 17 political activists known as the Luanda Book Club received prison sentences for plotting to overthrow Angola\u2019s government.", "source": "The New York Times", "lead_paragraph": "A group of 17 political activists known as the Luanda Book Club received prison sentences for plotting to overthrow Angola\u2019s government.", "word_count": "116", "pub_date": "2016-03-30T00:00:00Z", "subsection_name": "Africa", "blog": [], "type_of_material": "Brief", "section_name": "World", "web_url": "http://www.nytimes.com/2016/03/30/world/africa/angola-members-of-book-club-are-convicted-of-plotting-a-coup.html", "_id": "56fb1fda38f0d816b6b7e28a"}