{"web_url": "http://www.nytimes.com/reuters/2016/11/08/sports/soccer/08reuters-soccer-worldcup-eng-sco-kane.html", "pub_date": "2016-11-08T14:54:27Z", "byline": {"person": [], "organization": "REUTERS", "original": "By REUTERS"}, "keywords": [], "section_name": "Sports", "document_type": "article", "lead_paragraph": "England striker Harry Kane says he is ready to face Scotland in a World Cup qualifier on Friday despite having played only 70 minutes of football since injuring his ankle seven weeks ago.", "slideshow_credits": null, "headline": {"print_headline": "Kane Able to Face Scotland Despite Lack of Football", "main": "Kane Able to Face Scotland Despite Lack of Football"}, "snippet": "England striker Harry Kane says he is ready to face Scotland in a World Cup qualifier on Friday despite having played only 70 minutes of football since injuring his ankle seven weeks ago....", "abstract": null, "news_desk": null, "blog": [], "word_count": "265", "multimedia": [], "source": "Reuters", "print_page": null, "_id": "5821e72f95d0e0204d55f51e", "subsection_name": "Soccer", "type_of_material": "News"}