{"web_url": "http://www.nytimes.com/reuters/2016/12/04/sports/soccer/04reuters-soccer-england-bou-liv-ake.html", "pub_date": "2016-12-04T17:30:31+0000", "byline": {"person": [], "organization": "REUTERS", "original": "By REUTERS"}, "keywords": [], "section_name": "Sports", "document_type": "article", "lead_paragraph": "Of the extraordinary total of 38 Chelsea players out on loan to other clubs this season, none can have done the Londoners a bigger favour than Nathan Ake, whose dramatic stoppage-time goal brought Bournemouth a 4-3 win over Liverpool on Sunday.", "slideshow_credits": null, "headline": {"print_headline": "Chelsea Loanee Ake Leaves Liverpool Feeling Blue", "main": "Chelsea Loanee Ake Leaves Liverpool Feeling Blue"}, "snippet": "Of the extraordinary total of 38 Chelsea players out on loan to other clubs this season, none can have done the Londoners a bigger favour than Nathan Ake, whose dramatic stoppage-time goal brought Bournemouth a 4-3 win over Liverpool on Sunday....", "abstract": null, "news_desk": null, "blog": [], "word_count": "393", "multimedia": [], "source": "Reuters", "print_page": null, "_id": "584452c795d0e03926074014", "subsection_name": "Soccer", "type_of_material": "News"}