{"web_url": "http://www.nytimes.com/reuters/2016/12/20/sports/soccer/20reuters-soccer-england-che-matic.html", "pub_date": "2016-12-20T08:10:19+0000", "byline": {"person": [], "organization": "REUTERS", "original": "By REUTERS"}, "keywords": [], "section_name": "Sports", "document_type": "article", "lead_paragraph": "Michy Batshuayi will be ready to grab his chance if selected to replace the suspended Diego Costa for Chelsea's Boxing Day clash with Bournemouth in the Premier League, said midfielder Nemanja Matic.", "slideshow_credits": null, "headline": {"print_headline": "Matic Backs Batshuayi to Fill In for Costa", "main": "Matic Backs Batshuayi to Fill In for Costa"}, "snippet": "Michy Batshuayi will be ready to grab his chance if selected to replace the suspended Diego Costa for Chelsea's Boxing Day clash with Bournemouth in the Premier League, said midfielder Nemanja Matic....", "abstract": null, "news_desk": null, "blog": [], "word_count": "248", "multimedia": [], "source": "Reuters", "print_page": null, "_id": "5858e77495d0e03926076e93", "subsection_name": "Soccer", "type_of_material": "News"}