{"image_url": "https://s3-media3.fl.yelpcdn.com/bphoto/A0nndnzs5vX0PXIbIw-YKg/o.jpg", "term": "attractions", "is_closed": false, "categories": [{"title": "Bookstores", "alias": "bookstores"}, {"title": "Comic Books", "alias": "comicbooks"}, {"title": "Cards & Stationery", "alias": "stationery"}], "url": "https://www.yelp.com/biz/magma-manchester?adjust_creative=92p07_JjKyriZTQxAXRiKQ&utm_campaign=yelp_api_v3&utm_medium=api_v3_business_lookup&utm_source=92p07_JjKyriZTQxAXRiKQ", "is_claimed": false, "phone": "+441612368777", "name": "Magma", "photos": ["https://s3-media2.fl.yelpcdn.com/bphoto/A0nndnzs5vX0PXIbIw-YKg/o.jpg", "https://s3-media2.fl.yelpcdn.com/bphoto/5jrRbIVKPPiIL8h_XY3TxA/o.jpg", "https://s3-media3.fl.yelpcdn.com/bphoto/3XlkocqX1OjcpWOuBL2Mqw/o.jpg"], "rating": 4.5, "location": {"city": "Manchester", "address2": "", "address1": "22 Oldham Street", "address3": "", "state": "XGM", "zip_code": "M1 1JN", "country": "GB"}, "price": "\u00a3\u00a3", "hours": [{"is_open_now": false, "open": [{"is_overnight": false, "day": 0, "start": "1000", "end": "1830"}, {"is_overnight": false, "day": 1, "start": "1000", "end": "1830"}, {"is_overnight": false, "day": 2, "start": "1000", "end": "1830"}, {"is_overnight": false, "day": 3, "start": "1000", "end": "1830"}, {"is_overnight": false, "day": 4, "start": "1000", "end": "1830"}, {"is_overnight": false, "day": 5, "start": "1000", "end": "1830"}, {"is_overnight": false, "day": 6, "start": "1200", "end": "1700"}], "hours_type": "REGULAR"}], "id": "magma-manchester", "coordinates": {"latitude": 53.4825893, "longitude": -2.2354026}, "review_count": 22}