{"document_type": "multimedia", "byline": [], "news_desk": "Food", "slideshow_credits": "Horacio Paone for The New York Times", "abstract": null, "multimedia": [{"type": "image", "url": "images/2016/02/17/dining/17POUR-slide-JKQJ/17POUR-slide-JKQJ-thumbWide.jpg", "legacy": {"wide": "images/2016/02/17/dining/17POUR-slide-JKQJ/17POUR-slide-JKQJ-thumbWide.jpg", "wideheight": "126", "widewidth": "190"}, "width": 190, "subtype": "wide", "height": 126}, {"type": "image", "url": "images/2016/02/17/dining/17POUR-slide-JKQJ/17POUR-slide-JKQJ-articleLarge.jpg", "legacy": {"xlarge": "images/2016/02/17/dining/17POUR-slide-JKQJ/17POUR-slide-JKQJ-articleLarge.jpg", "xlargewidth": "600", "xlargeheight": "400"}, "width": 600, "subtype": "xlarge", "height": 400}, {"type": "image", "url": "images/2016/02/17/dining/17POUR-slide-JKQJ/17POUR-slide-JKQJ-thumbStandard.jpg", "legacy": {"thumbnail": "images/2016/02/17/dining/17POUR-slide-JKQJ/17POUR-slide-JKQJ-thumbStandard.jpg", "thumbnailwidth": "75", "thumbnailheight": "75"}, "width": 75, "subtype": "thumbnail", "height": 75}], "headline": {"main": "The Nuances of Mendoza"}, "print_page": null, "keywords": [{"value": "Wines", "is_major": "N", "rank": "1", "name": "subject"}, {"value": "Mendoza (Argentina)", "is_major": "N", "rank": "2", "name": "glocations"}], "snippet": "A growing number of Argentine producers are trying to move beyond traditionally fruity wines to explore the subtleties of the region\u2019s terroir.", "source": "The New York Times", "lead_paragraph": "A growing number of Argentine producers are trying to move beyond traditionally fruity wines to explore the subtleties of the region\u2019s terroir.", "word_count": "22", "pub_date": "2016-02-17T00:00:00Z", "subsection_name": null, "blog": [], "type_of_material": "Slideshow", "section_name": "Food", "web_url": "http://www.nytimes.com/slideshow/2016/02/17/dining/wine-mendoza.html", "_id": "56bcde7038f0d810e6a1a1b7"}