{"term": "attractions", "phone": "+33145777200", "categories": [{"alias": "hotels", "title": "Hotels"}], "url": "https://www.yelp.com/biz/mercure-paris-plaza-pont-mirabeau-hotel-paris?adjust_creative=92p07_JjKyriZTQxAXRiKQ&utm_campaign=yelp_api_v3&utm_medium=api_v3_business_lookup&utm_source=92p07_JjKyriZTQxAXRiKQ", "is_claimed": false, "is_closed": false, "name": "Mercure Paris Plaza Pont Mirabeau Hotel", "photos": ["https://s3-media2.fl.yelpcdn.com/bphoto/KZxAMggq64o8QzwqnOnkkA/o.jpg", "https://s3-media2.fl.yelpcdn.com/bphoto/PWlKVBK7ywEGjDvsLZsfcg/o.jpg", "https://s3-media1.fl.yelpcdn.com/bphoto/RJanhcXlTyPcX-BACsDoEg/o.jpg"], "rating": 4.5, "image_url": "https://s3-media1.fl.yelpcdn.com/bphoto/KZxAMggq64o8QzwqnOnkkA/o.jpg", "price": "\u20ac\u20ac", "review_count": 2, "id": "mercure-paris-plaza-pont-mirabeau-hotel-paris", "location": {"city": "Paris", "address2": "", "address1": "10 ave Emile Zola", "address3": "", "state": "75", "zip_code": "75015", "country": "FR"}, "coordinates": {"latitude": 48.846074717199, "longitude": 2.27882338576315}}