{"abstract": null, "web_url": "http://www.nytimes.com/aponline/2016/02/01/sports/ncaafootball/ap-fbc-destination-mississippi.html", "byline": {"original": "By THE ASSOCIATED PRESS", "person": [], "organization": "THE ASSOCIATED PRESS"}, "subsection_name": "College Football", "type_of_material": "News", "lead_paragraph": "Mississippi has made a rapid rise into the upper tier of the Southeastern Conference in the standings and on the recruiting trail.", "_id": "56afd45e38f0d849125592fa", "word_count": "705", "news_desk": "None", "print_page": null, "keywords": [], "multimedia": [], "headline": {"print_headline": "For Ole Miss, Winning and Recruiting Go Hand-In-Hand", "main": "For Ole Miss, Winning and Recruiting Go Hand-In-Hand"}, "pub_date": "2016-02-01T16:52:49Z", "slideshow_credits": null, "document_type": "article", "source": "AP", "snippet": "Mississippi has made a rapid rise into the upper tier of the Southeastern Conference in the standings and on the recruiting trail....", "blog": [], "section_name": "Sports"}