{"abstract": null, "web_url": "http://www.nytimes.com/reuters/2016/04/30/sports/autoracing/30reuters-motor-f1-russia-practice.html", "byline": {"original": "By REUTERS", "person": [], "organization": "REUTERS"}, "subsection_name": "Auto Racing", "type_of_material": "News", "lead_paragraph": "Formula One world champion Lewis Hamilton prepared for Russian Grand Prix qualifying with the fastest lap yet of the Sochi circuit in Saturday's final practice.", "_id": "57248c1638f0d83e7bbb58b2", "word_count": "207", "news_desk": "None", "print_page": null, "keywords": [], "multimedia": [], "headline": {"print_headline": "Hamilton Faster Than Ever in Final Sochi Practice", "main": "Hamilton Faster Than Ever in Final Sochi Practice"}, "pub_date": "2016-04-30T06:39:55Z", "slideshow_credits": null, "document_type": "article", "source": "Reuters", "snippet": "Formula One world champion Lewis Hamilton prepared for Russian Grand Prix qualifying with the fastest lap yet of the Sochi circuit in Saturday's final practice....", "blog": [], "section_name": "Sports"}