{"document_type": "article", "byline": [], "news_desk": "Society", "slideshow_credits": null, "abstract": null, "multimedia": [{"type": "image", "url": "images/2016/07/03/fashion/weddings/03HELB/03HELB-thumbWide-v2.jpg", "legacy": {"wide": "images/2016/07/03/fashion/weddings/03HELB/03HELB-thumbWide-v2.jpg", "wideheight": "126", "widewidth": "190"}, "width": 190, "subtype": "wide", "height": 126}, {"type": "image", "url": "images/2016/07/03/fashion/weddings/03HELB/03HELB-articleLarge-v2.jpg", "legacy": {"xlarge": "images/2016/07/03/fashion/weddings/03HELB/03HELB-articleLarge-v2.jpg", "xlargewidth": "600", "xlargeheight": "355"}, "width": 600, "subtype": "xlarge", "height": 355}, {"type": "image", "url": "images/2016/07/03/fashion/weddings/03HELB/03HELB-thumbStandard.jpg", "legacy": {"thumbnail": "images/2016/07/03/fashion/weddings/03HELB/03HELB-thumbStandard.jpg", "thumbnailwidth": "75", "thumbnailheight": "75"}, "width": 75, "subtype": "thumbnail", "height": 75}], "headline": {"print_headline": "Kristina Helb,  Brendan Derr", "main": "Kristina Helb, Brendan Derr"}, "print_page": "21", "keywords": [{"value": "Weddings and Engagements", "is_major": "N", "rank": "1", "name": "subject"}], "snippet": "The couple met in 2013 through the dating app Hinge....", "source": "The New York Times", "lead_paragraph": "The couple met in 2013 through the dating app Hinge.", "word_count": "151", "pub_date": "2016-07-03T00:00:00Z", "subsection_name": "Weddings", "blog": [], "type_of_material": "News", "section_name": "Fashion & Style", "web_url": "http://www.nytimes.com/2016/07/03/fashion/weddings/kristina-helb-brendan-derr.html", "_id": "5778914f38f0d8343812c0f7"}