{"document_type": "multimedia", "byline": [], "news_desk": "Real Estate", "slideshow_credits": "Regina Kokoszka for The New York Times", "abstract": null, "multimedia": [{"type": "image", "url": "images/2016/04/10/realestate/10WHATILOVE-slide-RVNS/10WHATILOVE-slide-RVNS-thumbWide.jpg", "legacy": {"wide": "images/2016/04/10/realestate/10WHATILOVE-slide-RVNS/10WHATILOVE-slide-RVNS-thumbWide.jpg", "wideheight": "126", "widewidth": "190"}, "width": 190, "subtype": "wide", "height": 126}, {"type": "image", "url": "images/2016/04/10/realestate/10WHATILOVE-slide-RVNS/10WHATILOVE-slide-RVNS-articleLarge.jpg", "legacy": {"xlarge": "images/2016/04/10/realestate/10WHATILOVE-slide-RVNS/10WHATILOVE-slide-RVNS-articleLarge.jpg", "xlargewidth": "600", "xlargeheight": "400"}, "width": 600, "subtype": "xlarge", "height": 400}, {"type": "image", "url": "images/2016/04/10/realestate/10WHATILOVE-slide-RVNS/10WHATILOVE-slide-RVNS-thumbStandard.jpg", "legacy": {"thumbnail": "images/2016/04/10/realestate/10WHATILOVE-slide-RVNS/10WHATILOVE-slide-RVNS-thumbStandard.jpg", "thumbnailwidth": "75", "thumbnailheight": "75"}, "width": 75, "subtype": "thumbnail", "height": 75}], "headline": {"main": "What I Love | Jonathan Rockefeller"}, "print_page": null, "keywords": [{"value": "Rockefeller, Jonathan W", "is_major": "N", "rank": "1", "name": "persons"}, {"value": "Carle, Eric", "is_major": "N", "rank": "2", "name": "persons"}, {"value": "Children and Childhood", "is_major": "N", "rank": "3", "name": "subject"}, {"value": "Puppets", "is_major": "N", "rank": "4", "name": "subject"}, {"value": "Real Estate and Housing (Residential)", "is_major": "N", "rank": "5", "name": "subject"}, {"value": "Interior Design and Furnishings", "is_major": "N", "rank": "6", "name": "subject"}, {"value": "Theater", "is_major": "N", "rank": "7", "name": "subject"}], "snippet": "Jonathan Rockefeller, the creator of \u201cThe Very Hungry Caterpillar Show,\u201d lives in Manhattan", "source": "The New York Times", "lead_paragraph": "Jonathan Rockefeller, the creator of \u201cThe Very Hungry Caterpillar Show,\u201d lives in Manhattan", "word_count": "13", "pub_date": "2016-04-08T20:05:35Z", "subsection_name": null, "blog": [], "type_of_material": "Slideshow", "section_name": "Real Estate", "web_url": "http://www.nytimes.com/slideshow/2016/04/10/realestate/what-i-love-jonathan-rockefeller.html", "_id": "5708164d38f0d82e060697f9"}