{"document_type": "multimedia", "byline": [], "news_desk": "Technology", "slideshow_credits": "Andrew Testa for The New York Times", "abstract": null, "multimedia": [{"type": "image", "url": "images/2016/06/20/business/20droneresponders-web01/20droneresponders-web01-thumbWide.jpg", "legacy": {"wide": "images/2016/06/20/business/20droneresponders-web01/20droneresponders-web01-thumbWide.jpg", "wideheight": "126", "widewidth": "190"}, "width": 190, "subtype": "wide", "height": 126}, {"type": "image", "url": "images/2016/06/20/business/20droneresponders-web01/20droneresponders-web01-articleLarge.jpg", "legacy": {"xlarge": "images/2016/06/20/business/20droneresponders-web01/20droneresponders-web01-articleLarge.jpg", "xlargewidth": "600", "xlargeheight": "401"}, "width": 600, "subtype": "xlarge", "height": 401}, {"type": "image", "url": "images/2016/06/20/business/20droneresponders-web01/20droneresponders-web01-thumbStandard.jpg", "legacy": {"thumbnail": "images/2016/06/20/business/20droneresponders-web01/20droneresponders-web01-thumbStandard.jpg", "thumbnailwidth": "75", "thumbnailheight": "75"}, "width": 75, "subtype": "thumbnail", "height": 75}], "headline": {"main": "Learning to Fly Drones to Help in Emergencies"}, "print_page": null, "keywords": [{"value": "Drones (Pilotless Planes)", "is_major": "N", "rank": "1", "name": "subject"}, {"value": "Emergency Medical Treatment", "is_major": "N", "rank": "2", "name": "subject"}], "snippet": "A group of workers is taking part in a trial to jump-start the use of unmanned aircraft by Europe\u2019s emergency services.", "source": "The New York Times", "lead_paragraph": "A group of workers is taking part in a trial to jump-start the use of unmanned aircraft by Europe\u2019s emergency services.", "word_count": "21", "pub_date": "2016-06-20T00:00:00Z", "subsection_name": null, "blog": [], "type_of_material": "Slideshow", "section_name": "Technology", "web_url": "http://www.nytimes.com/slideshow/2016/06/20/technology/learning-to-fly-drones-to-help-in-emergencies.html", "_id": "5767218a38f0d86ed7803ed7"}