{"abstract": null, "web_url": "http://www.nytimes.com/aponline/2016/04/06/sports/baseball/ap-bbn-padres-scoreless-streak.html", "byline": {"original": "By THE ASSOCIATED PRESS", "person": [], "organization": "THE ASSOCIATED PRESS"}, "subsection_name": "Baseball", "type_of_material": "News", "lead_paragraph": "The San Diego Padres have tied the major league record with 26 straight scoreless innings to start a season.", "_id": "5705db7038f0d86865ca531f", "word_count": "132", "news_desk": "None", "print_page": null, "keywords": [], "multimedia": [], "headline": {"print_headline": "Padres Tie MLB Record by Starting With 26 Scoreless Innings", "main": "Padres Tie MLB Record by Starting With 26 Scoreless Innings"}, "pub_date": "2016-04-06T23:57:52Z", "slideshow_credits": null, "document_type": "article", "source": "AP", "snippet": "The San Diego Padres have tied the major league record with 26 straight scoreless innings to start a season....", "blog": [], "section_name": "Sports"}