{"abstract": null, "web_url": "http://www.nytimes.com/aponline/2016/09/28/sports/baseball/ap-bbn-phillies-braves.html", "byline": {"original": "By THE ASSOCIATED PRESS", "person": [], "organization": "THE ASSOCIATED PRESS"}, "subsection_name": "Baseball", "type_of_material": "News", "lead_paragraph": "The Atlanta Braves are giving themselves plenty of reasons to be hopeful about 2017, from a surging offense to improved young pitching.", "_id": "57ec76b995d0e021d7988fa5", "word_count": null, "news_desk": "None", "print_page": null, "keywords": [], "multimedia": [], "headline": {"print_headline": "Freeman's Streak Reaches 30, Kemp Homers, Braves Rout Phils", "main": "Freeman's Streak Reaches 30, Kemp Homers, Braves Rout Phils"}, "pub_date": "2016-09-29T02:00:03Z", "slideshow_credits": null, "document_type": "article", "source": "", "snippet": "The Atlanta Braves are giving themselves plenty of reasons to be hopeful about 2017, from a surging offense to improved young pitching....", "blog": [], "section_name": "Sports"}