{"abstract": null, "web_url": "http://www.nytimes.com/aponline/2016/04/27/sports/tennis/ap-ten-estoril-open.html", "byline": {"original": "By THE ASSOCIATED PRESS", "person": [], "organization": "THE ASSOCIATED PRESS"}, "subsection_name": "Tennis", "type_of_material": "News", "lead_paragraph": "Second-seeded Nick Kyrgios of Australia beat Inigo Cervantes of Spain 7-6 (4), 7-5 to advance to the quarterfinals of the Estoril Open on Wednesday.", "_id": "5720f82c38f0d83acb9a5ff6", "word_count": "193", "news_desk": "None", "print_page": null, "keywords": [], "multimedia": [], "headline": {"print_headline": "Nick Kyrgios, Borna Coric in Quarterfinals of Estoril Open", "main": "Nick Kyrgios, Borna Coric in Quarterfinals of Estoril Open"}, "pub_date": "2016-04-27T13:31:08Z", "slideshow_credits": null, "document_type": "article", "source": "AP", "snippet": "Second-seeded Nick Kyrgios of Australia beat Inigo Cervantes of Spain 7-6 (4), 7-5 to advance to the quarterfinals of the Estoril Open on Wednesday....", "blog": [], "section_name": "Sports"}