{"image_url": "https://s3-media4.fl.yelpcdn.com/bphoto/QBPKQY_Ljr9ASrT8HMeGKQ/o.jpg", "is_closed": false, "categories": [{"title": "Breakfast & Brunch", "alias": "breakfast_brunch"}, {"title": "Coffee & Tea", "alias": "coffee"}], "review_count": 70, "is_claimed": true, "coordinates": {"latitude": -31.9336624443474, "longitude": 115.872502326965}, "phone": "+61893704883", "name": "Cantina 663", "photos": ["https://s3-media2.fl.yelpcdn.com/bphoto/QBPKQY_Ljr9ASrT8HMeGKQ/o.jpg", "https://s3-media4.fl.yelpcdn.com/bphoto/GuwUnEbHT0iEMIXezHIS9A/o.jpg", "https://s3-media4.fl.yelpcdn.com/bphoto/9e1cdvJrFge25P7gNDfn0g/o.jpg"], "rating": 4.0, "price": "$$", "hours": [{"is_open_now": true, "open": [{"is_overnight": false, "day": 0, "start": "0730", "end": "2230"}, {"is_overnight": false, "day": 1, "start": "0730", "end": "2230"}, {"is_overnight": false, "day": 2, "start": "0730", "end": "2230"}, {"is_overnight": false, "day": 3, "start": "0730", "end": "2230"}, {"is_overnight": false, "day": 4, "start": "0730", "end": "2300"}, {"is_overnight": false, "day": 5, "start": "0730", "end": "2300"}, {"is_overnight": false, "day": 6, "start": "0730", "end": "1500"}], "hours_type": "REGULAR"}], "location": {"city": "Mt Lawley", "address2": null, "address1": "663 Beaufort St", "address3": null, "state": "WA", "zip_code": "6050", "country": "AU"}, "id": "cantina-663-mt-lawley", "url": "https://www.yelp.com/biz/cantina-663-mt-lawley?adjust_creative=92p07_JjKyriZTQxAXRiKQ&utm_campaign=yelp_api_v3&utm_medium=api_v3_business_lookup&utm_source=92p07_JjKyriZTQxAXRiKQ", "term": "restaurants"}