{"coordinates": {"latitude": -27.469016, "longitude": 153.024616}, "photos": ["https://s3-media2.fl.yelpcdn.com/bphoto/lsgFK_wV_36d_NEa5gXiZQ/o.jpg", "https://s3-media1.fl.yelpcdn.com/bphoto/beYiTWiXKQ-5oq-9Ngik9g/o.jpg", "https://s3-media2.fl.yelpcdn.com/bphoto/Mgd_5yX0wWZfkK_VCS9bNg/o.jpg"], "id": "mos-burger-brisbane", "phone": "+61730129969", "review_count": 26, "is_closed": false, "image_url": "https://s3-media3.fl.yelpcdn.com/bphoto/lsgFK_wV_36d_NEa5gXiZQ/o.jpg", "rating": 4.0, "price": "$", "is_claimed": false, "hours": [{"hours_type": "REGULAR", "open": [{"day": 0, "end": "2200", "is_overnight": false, "start": "0730"}, {"day": 1, "end": "2200", "is_overnight": false, "start": "0730"}, {"day": 2, "end": "2200", "is_overnight": false, "start": "0730"}, {"day": 3, "end": "2200", "is_overnight": false, "start": "0730"}, {"day": 4, "end": "2300", "is_overnight": false, "start": "0730"}, {"day": 5, "end": "2100", "is_overnight": false, "start": "1000"}, {"day": 6, "end": "2000", "is_overnight": false, "start": "1000"}], "is_open_now": true}], "url": "https://www.yelp.com/biz/mos-burger-brisbane?adjust_creative=92p07_JjKyriZTQxAXRiKQ&utm_campaign=yelp_api_v3&utm_medium=api_v3_business_lookup&utm_source=92p07_JjKyriZTQxAXRiKQ", "term": "restaurants", "location": {"address3": "", "zip_code": "4000", "address2": "79 Adelaide St", "address1": "Shop 8", "city": "Brisbane", "country": "AU", "state": "QLD"}, "name": "MOS Burger", "categories": [{"title": "Burgers", "alias": "burgers"}, {"title": "Japanese", "alias": "japanese"}, {"title": "Fast Food", "alias": "hotdogs"}]}