{"document_type": "article", "byline": {"contributor": "", "person": [], "organization": "THE ASSOCIATED PRESS", "original": "By THE ASSOCIATED PRESS"}, "news_desk": "Sports", "slideshow_credits": null, "abstract": "MLB Roundup; Philadelphia Phillies defeat Cleveland Indians, 4-3; other baseball news noted.", "multimedia": [{"type": "image", "url": "images/2016/05/01/sports/01bats/01bats-thumbWide.jpg", "legacy": {"wide": "images/2016/05/01/sports/01bats/01bats-thumbWide.jpg", "wideheight": "126", "widewidth": "190"}, "width": 190, "subtype": "wide", "height": 126}, {"type": "image", "url": "images/2016/05/01/sports/01bats/01bats-articleLarge.jpg", "legacy": {"xlarge": "images/2016/05/01/sports/01bats/01bats-articleLarge.jpg", "xlargewidth": "600", "xlargeheight": "418"}, "width": 600, "subtype": "xlarge", "height": 418}, {"type": "image", "url": "images/2016/05/01/sports/01bats/01bats-thumbStandard.jpg", "legacy": {"thumbnail": "images/2016/05/01/sports/01bats/01bats-thumbStandard.jpg", "thumbnailwidth": "75", "thumbnailheight": "75"}, "width": 75, "subtype": "thumbnail", "height": 75}], "headline": {"kicker": "Roundup", "content_kicker": "Roundup", "print_headline": "Phillies\u2019 Streak Reaches Five as They Outlast the Indians", "main": "Phillies\u2019 Streak Reaches Five as They Outlast the Indians"}, "print_page": "4", "keywords": [{"value": "Baseball", "is_major": "Y", "rank": "1", "name": "subject"}, {"value": "Philadelphia Phillies", "is_major": "Y", "rank": "2", "name": "organizations"}, {"value": "Cleveland Indians", "is_major": "Y", "rank": "3", "name": "organizations"}, {"value": "Galvis, Freddy (1989- )", "is_major": "N", "rank": "4", "name": "persons"}], "snippet": "Freddy Galvis homered and hit a go-ahead single in the seventh inning Saturday night to lead the host Philadelphia Phillies to their fifth straight win, 4-3, over the Cleveland Indians.", "source": "The New York Times", "lead_paragraph": "Freddy Galvis homered and hit a go-ahead single in the seventh inning Saturday night to lead the host Philadelphia Phillies to their fifth straight win, 4-3, over the Cleveland Indians.", "word_count": "659", "pub_date": "2016-05-01T04:25:52Z", "subsection_name": "Baseball", "blog": [], "type_of_material": "News", "section_name": "Sports", "web_url": "http://www.nytimes.com/2016/05/01/sports/baseball/phillies-streak-reaches-five-as-they-outlast-the-indians.html", "_id": "5725855638f0d83e2a5151d7"}