{"document_type": "article", "byline": [], "news_desk": "Society", "slideshow_credits": null, "abstract": null, "multimedia": [{"type": "image", "url": "images/2016/01/17/fashion/weddings/17WAINWRIGHTjpg/17WAINWRIGHTjpg-thumbWide-v2.jpg", "legacy": {"wide": "images/2016/01/17/fashion/weddings/17WAINWRIGHTjpg/17WAINWRIGHTjpg-thumbWide-v2.jpg", "wideheight": "126", "widewidth": "190"}, "width": 190, "subtype": "wide", "height": 126}, {"type": "image", "url": "images/2016/01/17/fashion/weddings/17WAINWRIGHTjpg/17WAINWRIGHTjpg-articleLarge-v2.jpg", "legacy": {"xlarge": "images/2016/01/17/fashion/weddings/17WAINWRIGHTjpg/17WAINWRIGHTjpg-articleLarge-v2.jpg", "xlargewidth": "600", "xlargeheight": "354"}, "width": 600, "subtype": "xlarge", "height": 354}, {"type": "image", "url": "images/2016/01/17/fashion/weddings/17WAINWRIGHTjpg/17WAINWRIGHTjpg-thumbStandard.jpg", "legacy": {"thumbnail": "images/2016/01/17/fashion/weddings/17WAINWRIGHTjpg/17WAINWRIGHTjpg-thumbStandard.jpg", "thumbnailwidth": "75", "thumbnailheight": "75"}, "width": 75, "subtype": "thumbnail", "height": 75}], "headline": {"print_headline": "Nina Wainwright, Nathan Strauss", "main": "Nina Wainwright, Nathan Strauss"}, "print_page": "13", "keywords": [{"value": "Weddings and Engagements", "is_major": "N", "rank": "1", "name": "subject"}], "snippet": "The bride, an interior designer, and the groom, a lawyer, were wed at Maidstone Club in East Hampton, N.Y.", "source": "The New York Times", "lead_paragraph": "The bride, an interior designer, and the groom, a lawyer, were wed at Maidstone Club in East Hampton, N.Y.", "word_count": "173", "pub_date": "2016-01-17T00:00:00Z", "subsection_name": "Weddings", "blog": [], "type_of_material": "News", "section_name": "Fashion & Style", "web_url": "http://www.nytimes.com/2016/01/17/fashion/weddings/nina-wainwright-nathan-strauss.html", "_id": "569b248838f0d80d6e342094"}