{"document_type": "article", "byline": [], "news_desk": "Letters", "slideshow_credits": null, "abstract": null, "multimedia": [{"type": "image", "url": "images/2016/01/23/opinion/23LkristofWeb/23kristofWeb-thumbWide.jpg", "legacy": {"wide": "images/2016/01/23/opinion/23LkristofWeb/23kristofWeb-thumbWide.jpg", "wideheight": "126", "widewidth": "190"}, "width": 190, "subtype": "wide", "height": 126}, {"type": "image", "url": "images/2016/01/23/opinion/23LkristofWeb/23kristofWeb-articleLarge.jpg", "legacy": {"xlarge": "images/2016/01/23/opinion/23LkristofWeb/23kristofWeb-articleLarge.jpg", "xlargewidth": "600", "xlargeheight": "400"}, "width": 600, "subtype": "xlarge", "height": 400}, {"type": "image", "url": "images/2016/01/23/opinion/23LkristofWeb/23kristofWeb-thumbStandard.jpg", "legacy": {"thumbnail": "images/2016/01/23/opinion/23LkristofWeb/23kristofWeb-thumbStandard.jpg", "thumbnailwidth": "75", "thumbnailheight": "75"}, "width": 75, "subtype": "thumbnail", "height": 75}], "headline": {"kicker": "Letters", "content_kicker": "Letters", "print_headline": "In Gun Debate, the Sides Aren\u2019t Equal", "main": "In Gun Debate, the Sides Aren\u2019t Equal"}, "print_page": "18", "keywords": [{"value": "Gun Control", "is_major": "N", "rank": "1", "name": "subject"}, {"value": "National Rifle Assn", "is_major": "N", "rank": "2", "name": "organizations"}, {"value": "United States Politics and Government", "is_major": "N", "rank": "3", "name": "subject"}], "snippet": "Readers take issue with Nicholas Kristof\u2019s stress on gun safety instead of gun control.", "source": "The New York Times", "lead_paragraph": "Readers take issue with Nicholas Kristof\u2019s stress on gun safety instead of gun control.", "word_count": "666", "pub_date": "2016-01-23T00:00:00Z", "subsection_name": null, "blog": [], "type_of_material": "Letter", "section_name": "Opinion", "web_url": "http://www.nytimes.com/2016/01/23/opinion/in-gun-debate-the-sides-arent-equal.html", "_id": "56a27ffe38f0d85aa1bb1882"}