{"image_url": "", "phone": "+6494869170", "categories": [{"title": "Hotels", "alias": "hotels"}], "review_count": 0, "is_claimed": false, "is_closed": false, "name": "City of Sails Motel", "photos": [], "rating": 0.0, "id": "city-of-sails-motel-auckland", "location": {"city": "Auckland", "address2": null, "address1": "219 Shakespeare Rd", "address3": null, "state": "AUK", "zip_code": "0620", "country": "NZ"}, "coordinates": {"latitude": -36.7821007, "longitude": 174.7529297}, "url": "https://www.yelp.com/biz/city-of-sails-motel-auckland?adjust_creative=92p07_JjKyriZTQxAXRiKQ&utm_campaign=yelp_api_v3&utm_medium=api_v3_business_lookup&utm_source=92p07_JjKyriZTQxAXRiKQ", "term": "hotels"}