{"document_type": "multimedia", "byline": [], "news_desk": "Sports", "slideshow_credits": "Lianne Milton for The New York Times", "abstract": null, "multimedia": [{"type": "image", "url": "images/2016/09/16/sports/16PROSTHETICSweb1/16PROSTHETICSweb1-thumbWide.jpg", "legacy": {"wide": "images/2016/09/16/sports/16PROSTHETICSweb1/16PROSTHETICSweb1-thumbWide.jpg", "wideheight": "126", "widewidth": "190"}, "width": 190, "subtype": "wide", "height": 126}, {"type": "image", "url": "images/2016/09/16/sports/16PROSTHETICSweb1/16PROSTHETICSweb1-articleLarge.jpg", "legacy": {"xlarge": "images/2016/09/16/sports/16PROSTHETICSweb1/16PROSTHETICSweb1-articleLarge.jpg", "xlargewidth": "600", "xlargeheight": "400"}, "width": 600, "subtype": "xlarge", "height": 400}, {"type": "image", "url": "images/2016/09/16/sports/16PROSTHETICSweb1/16PROSTHETICSweb1-thumbStandard.jpg", "legacy": {"thumbnail": "images/2016/09/16/sports/16PROSTHETICSweb1/16PROSTHETICSweb1-thumbStandard.jpg", "thumbnailwidth": "75", "thumbnailheight": "75"}, "width": 75, "subtype": "thumbnail", "height": 75}], "headline": {"main": "Helping Hands for Damaged Limbs, and Wheels"}, "print_page": null, "keywords": [{"value": "Paralympic Games", "is_major": "N", "rank": "1", "name": "subject"}, {"value": "Prostheses", "is_major": "N", "rank": "2", "name": "subject"}, {"value": "Rio de Janeiro (Brazil)", "is_major": "N", "rank": "3", "name": "glocations"}], "snippet": "Technicians at a workshop at the Paralympics in Rio de Janeiro provide free repairs to the wheelchairs and prosthetics used by competitors at the Games....", "source": "The New York Times", "lead_paragraph": "Technicians at a workshop at the Paralympics in Rio de Janeiro provide free repairs to the wheelchairs and prosthetics used by competitors at the Games.", "word_count": "25", "pub_date": "2016-09-16T04:00:00+0000", "subsection_name": null, "blog": [], "type_of_material": "Slideshow", "section_name": "Sports", "web_url": "http://www.nytimes.com/slideshow/2016/09/16/sports/paralympics-prosthetics-rio-games.html", "_id": "57da621095d0e021d798659c"}